igninterage/__init__.py
igninterage/exceptions.py
igninterage/ign_interage.py
igninterage/interage.py
igninterage/utils.py
igninterage-1.2.1.dist-info/LICENSE
igninterage-1.2.1.dist-info/METADATA
igninterage-1.2.1.dist-info/WHEEL
igninterage-1.2.1.dist-info/top_level.txt
igninterage-1.2.1.dist-info/RECORD
