Metadata-Version: 2.1
Name: igninterage
Version: 1.2.1
Summary: Modulo para interagir no forum IGNboards+
Home-page: https://github.com/psychodinae/Igninterage
Author: Psychodinae
Author-email: noteprof213@gmail.com
License: UNKNOWN
Platform: UNKNOWN
Classifier: Programming Language :: Python :: 3.6
Classifier: Operating System :: Microsoft :: Windows
Classifier: Operating System :: POSIX :: Linux
Classifier: License :: OSI Approved :: MIT License
Requires-Python: >=3.6
Requires-Dist: requests
Requires-Dist: lxml
Requires-Dist: secretstorage
Requires-Dist: cryptography
Requires-Dist: pywin32 ; platform_system == "Windows"
